README.txt
setup.py
zxs/__init__.py
zxs/__main__.py
zxs/zxs.py
zxs.egg-info/PKG-INFO
zxs.egg-info/SOURCES.txt
zxs.egg-info/dependency_links.txt
zxs.egg-info/entry_points.txt
zxs.egg-info/not-zip-safe
zxs.egg-info/top_level.txt