Metadata-Version: 1.0
Name: zxs
Version: 11
Summary: A package for data science made easy
Home-page: https://github.com/zxs107020/zxs
Author: zxs107020
Author-email: zxs107020@gmail.com
License: self
Platform: UNKNOWN
